dgut_requests/__init__.py
dgut_requests/dgut.py
dgut_requests-2.1.0.dist-info/LICENSE
dgut_requests-2.1.0.dist-info/METADATA
dgut_requests-2.1.0.dist-info/WHEEL
dgut_requests-2.1.0.dist-info/top_level.txt
dgut_requests-2.1.0.dist-info/RECORD
