Metadata-Version: 2.1
Name: dgut-requests
Version: 2.1.0
Summary: 用requests等库封装的东莞理工学院相关系统的爬虫脚本库，亦是东莞理工学院第一个pypi的爬虫库
Home-page: https://github.com/BertraMoon/dgut-requests
Author: Bertramoon
Author-email: bertramoon@126.com
Project-URL: Bug Tracker, https://github.com/BertraMoon/dgut-requests/issues
Classifier: Programming Language :: Python :: 3
Classifier: License :: OSI Approved :: BSD License
Classifier: Operating System :: OS Independent
Requires-Python: >=3.7
License-File: LICENSE
Requires-Dist: requests (>=2.25.1)
Requires-Dist: lxml (>=4.6.3)
Requires-Dist: pycryptodome (>=3.15.0)
